myfxbook/__init__.py
myfxbook/myfxbook.py
myfxbook-0.1.dist-info/METADATA
myfxbook-0.1.dist-info/WHEEL
myfxbook-0.1.dist-info/top_level.txt
myfxbook-0.1.dist-info/RECORD
